binance_syncer/__init__.py
binance_syncer/binance_data_sync.py
binance_syncer/cli.py
binance_syncer/constant.py
binance_syncer/utils.py
binance_syncer-0.2.3.dist-info/METADATA
binance_syncer-0.2.3.dist-info/WHEEL
binance_syncer-0.2.3.dist-info/entry_points.txt
binance_syncer-0.2.3.dist-info/licenses/LICENSE
binance_syncer-0.2.3.dist-info/RECORD
