Metadata-Version: 2.4
Name: binance_syncer
Version: 0.2.3
Summary: A high-performance synchronization tool for downloading and managing Binance historical data (klines, trades, etc.) asynchronously. It supports both local and S3 storage with intelligent data optimization (monthly vs daily preference).
License-File: LICENSE
Requires-Python: >=3.9
Requires-Dist: aiofiles>=24.1.0
Requires-Dist: aiohttp>=3.12.14
Requires-Dist: boto3>=1.39.8
Requires-Dist: bs4>=0.0.2
Requires-Dist: certifi>=2025.7.14
Requires-Dist: pandas>=2.3.0
Requires-Dist: pyarrow>=20.0.0
Requires-Dist: requests>=2.32.4
Requires-Dist: rich>=14.0.0
Requires-Dist: utilities-toolkit>=0.2.0
